neko_image_gallery_app/__init__.py
neko_image_gallery_app/asgi.py
neko_image_gallery_app/static/apple-touch-icon.png
neko_image_gallery_app/static/favicon.png
neko_image_gallery_app/static/index.html
neko_image_gallery_app/static/manifest.webmanifest
neko_image_gallery_app/static/pwa-192.png
neko_image_gallery_app/static/pwa-512.png
neko_image_gallery_app/static/registerSW.js
neko_image_gallery_app/static/sw.js
neko_image_gallery_app/static/workbox-5ffe50d4.js
neko_image_gallery_app/static/assets/index-CvuBezKI.js
neko_image_gallery_app/static/assets/index-DncD9EF6.css
neko_image_gallery_app-0.1.0.dev20250809135801.dist-info/METADATA
neko_image_gallery_app-0.1.0.dev20250809135801.dist-info/WHEEL
neko_image_gallery_app-0.1.0.dev20250809135801.dist-info/RECORD
